<?xml version="1.0" encoding="utf-8"?>
<StructureDefinition xmlns="http://hl7.org/fhir">
  <meta>
    <lastUpdated value="2018-03-04T16:06:30.187+00:00" />
  </meta>
  <url value="https://fhir.nhs.uk/STU3/StructureDefinition/DCH-NewbornBloodSpotScreening-DiagnosticReport-1" />
  <name value="DCH-NewBornBloodSpotScreening-DiagnosticReport-1" />
  <status value="draft" />
  <date value="2018-02-02T14:29:21.258+00:00" />
  <fhirVersion value="3.0.1" />
  <kind value="resource" />
  <abstract value="false" />
  <type value="DiagnosticReport" />
  <baseDefinition value="http://hl7.org/fhir/StructureDefinition/DiagnosticReport" />
  <derivation value="constraint" />
  <differential>
    <element id="DiagnosticReport.identifier">
      <path value="DiagnosticReport.identifier" />
      <min value="1" />
      <max value="1" />
    </element>
    <element id="DiagnosticReport.identifier.use">
      <path value="DiagnosticReport.identifier.use" />
      <max value="0" />
    </element>
    <element id="DiagnosticReport.identifier.type">
      <path value="DiagnosticReport.identifier.type" />
      <max value="0" />
    </element>
    <element id="DiagnosticReport.identifier.system">
      <path value="DiagnosticReport.identifier.system" />
      <min value="1" />
    </element>
    <element id="DiagnosticReport.identifier.value">
      <path value="DiagnosticReport.identifier.value" />
      <min value="1" />
    </element>
    <element id="DiagnosticReport.identifier.period">
      <path value="DiagnosticReport.identifier.period" />
      <max value="0" />
    </element>
    <element id="DiagnosticReport.identifier.assigner">
      <path value="DiagnosticReport.identifier.assigner" />
      <max value="0" />
    </element>
    <element id="DiagnosticReport.basedOn">
      <path value="DiagnosticReport.basedOn" />
      <max value="1" />
      <type>
        <code value="Reference" />
        <profile value="https://fhir.nhs.uk/STU3/StructureDefinition/DCH-NewbornBloodSpotScreening-ProcedureRequest-1" />
      </type>
    </element>
    <element id="DiagnosticReport.category">
      <path value="DiagnosticReport.category" />
      <max value="0" />
    </element>
    <element id="DiagnosticReport.subject">
      <path value="DiagnosticReport.subject" />
      <min value="1" />
      <type>
        <code value="Reference" />
        <targetProfile value="https://fhir.nhs.uk/STU3/StructureDefinition/CareConnect-DCH-Patient-1" />
      </type>
    </element>
    <element id="DiagnosticReport.subject.reference">
      <path value="DiagnosticReport.subject.reference" />
      <min value="1" />
    </element>
    <element id="DiagnosticReport.context">
      <path value="DiagnosticReport.context" />
      <min value="1" />
      <type>
        <code value="Reference" />
        <targetProfile value="https://fhir.nhs.uk/STU3/StructureDefinition/CareConnect-DCH-Encounter-1" />
      </type>
    </element>
    <element id="DiagnosticReport.context.reference">
      <path value="DiagnosticReport.context.reference" />
      <min value="1" />
    </element>
    <element id="DiagnosticReport.effective[x]:effectiveDateTime">
      <path value="DiagnosticReport.effectiveDateTime" />
      <sliceName value="effectiveDateTime" />
      <max value="0" />
      <type>
        <code value="dateTime" />
      </type>
    </element>
    <element id="DiagnosticReport.issued">
      <path value="DiagnosticReport.issued" />
      <min value="1" />
    </element>
    <element id="DiagnosticReport.performer">
      <path value="DiagnosticReport.performer" />
      <max value="0" />
    </element>
    <element id="DiagnosticReport.specimen">
      <path value="DiagnosticReport.specimen" />
      <max value="1" />
      <type>
        <code value="Reference" />
        <profile value="https://fhir.nhs.uk/STU3/StructureDefinition/DCH-NewbornBloodSpotScreening-Specimen-1" />
      </type>
    </element>
    <element id="DiagnosticReport.result">
      <path value="DiagnosticReport.result" />
      <short value="Blood spot screening outcomes" />
      <definition value="Procedure outcomes for the new born blood spot screening tests performed." />
      <min value="9" />
      <max value="9" />
      <type>
        <code value="Reference" />
        <targetProfile value="https://fhir.nhs.uk/STU3/StructureDefinition/CareConnect-DCH-NewbornBloodSpotScreeningPKU-Procedure-1" />
      </type>
      <type>
        <code value="Reference" />
        <targetProfile value="https://fhir.nhs.uk/STU3/StructureDefinition/CareConnect-DCH-NewbornBloodSpotScreeningSCD-Procedure-1" />
      </type>
      <type>
        <code value="Reference" />
        <targetProfile value="https://fhir.nhs.uk/STU3/StructureDefinition/CareConnect-DCH-NewbornBloodSpotScreeningCF-Procedure-1" />
      </type>
      <type>
        <code value="Reference" />
        <targetProfile value="https://fhir.nhs.uk/STU3/StructureDefinition/CareConnect-DCH-NewbornBloodSpotScreeningCHT-Procedure-1" />
      </type>
      <type>
        <code value="Reference" />
        <targetProfile value="https://fhir.nhs.uk/STU3/StructureDefinition/CareConnect-DCH-NewbornBloodSpotScreeningMCADD-Procedure-1" />
      </type>
      <type>
        <code value="Reference" />
        <targetProfile value="https://fhir.nhs.uk/STU3/StructureDefinition/CareConnect-DCH-NewbornBloodSpotScreeningHCU-Procedure-1" />
      </type>
      <type>
        <code value="Reference" />
        <targetProfile value="https://fhir.nhs.uk/STU3/StructureDefinition/CareConnect-DCH-NewbornBloodSpotScreeningMSUD-Procedure-1" />
      </type>
      <type>
        <code value="Reference" />
        <targetProfile value="https://fhir.nhs.uk/STU3/StructureDefinition/CareConnect-DCH-NewbornBloodSpotScreeningGA1-Procedure-1" />
      </type>
      <type>
        <code value="Reference" />
        <targetProfile value="https://fhir.nhs.uk/STU3/StructureDefinition/CareConnect-DCH-NewbornBloodSpotScreeningIVA-Procedure-1" />
      </type>
    </element>
    <element id="DiagnosticReport.result.reference">
      <path value="DiagnosticReport.result.reference" />
      <min value="1" />
    </element>
    <element id="DiagnosticReport.imagingStudy">
      <path value="DiagnosticReport.imagingStudy" />
      <max value="0" />
    </element>
    <element id="DiagnosticReport.image">
      <path value="DiagnosticReport.image" />
      <max value="0" />
    </element>
    <element id="DiagnosticReport.conclusion">
      <path value="DiagnosticReport.conclusion" />
      <max value="0" />
    </element>
    <element id="DiagnosticReport.codedDiagnosis">
      <path value="DiagnosticReport.codedDiagnosis" />
      <max value="0" />
    </element>
    <element id="DiagnosticReport.presentedForm">
      <path value="DiagnosticReport.presentedForm" />
      <max value="0" />
    </element>
  </differential>
</StructureDefinition>