<?xml version="1.0" encoding="UTF-8"?>
<ValueSet xmlns="http://hl7.org/fhir">
    <id value="RARecord-AdjustmentCategory-1"/>
    <url value="https://fhir.nhs.uk/STU3/ValueSet/RARecord-AdjustmentCategory-1"/>
    <version value="0.0.5"/>
    <name value="Reasonable Adjustments Record Adjustment Category"/>
    <status value="draft"/>
    <date value="2018-07-14T00:00:00+00:00"/>
    <publisher value="NHS Digital"/>
    <description value="A ValueSet to identify the category of a Reasonable Adjustment"/>
    <copyright value="© 2018 NHS Digital"/>
    <compose>
        <include>
            <system value="https://fhir.nhs.uk/STU3/CodeSystem/RARecord-AdjustmentCategory-1"/>
        </include>
    </compose>
</ValueSet>
